Metadata-Version: 2.1
Name: miau_mak
Version: 0.0.1
Summary: My Package
Author: Marina
Author-email: marina@icloud.com
